{"_index":".kibana_task_manager_1","_type":"_doc","_id":"task:Lens-lens_telemetry","_score":1,"_source":{"migrationVersion":{"task":"7.6.0"},"task":{"taskType":"lens_telemetry","retryAt":"2020-06-11T22:32:11.480Z","runAt":"2020-06-11T21:59:07.913Z","startedAt":"2020-06-11T22:16:11.480Z","state":"{\"byDate\":{},\"suggestionsByDate\":{},\"saved\":{},\"runs\":0}","params":"{}","ownerId":"kibana:36da57d5-466c-4937-808f-9ca8e62cbb66","scheduledAt":"2020-06-11T21:59:07.913Z","attempts":3,"status":"running"},"references":[],"updated_at":"2020-06-11T22:16:11.480Z","type":"task"}}
{"_index":".kibana_task_manager_1","_type":"_doc","_id":"task:oss_telemetry-vis_telemetry","_score":1,"_source":{"migrationVersion":{"task":"7.6.0"},"task":{"taskType":"vis_telemetry","retryAt":"2020-06-11T22:44:11.707Z","runAt":"2020-06-11T21:59:07.912Z","startedAt":"2020-06-11T22:24:11.707Z","state":"{\"stats\":{},\"runs\":0}","params":"{}","ownerId":"kibana:36da57d5-466c-4937-808f-9ca8e62cbb66","scheduledAt":"2020-06-11T21:59:07.912Z","attempts":3,"status":"running"},"references":[],"updated_at":"2020-06-11T22:24:11.707Z","type":"task"}}
{"_index":".kibana_task_manager_1","_type":"_doc","_id":"task:Alerting-alerting_telemetry","_score":1,"_source":{"migrationVersion":{"task":"7.6.0"},"task":{"taskType":"alerting_telemetry","retryAt":null,"runAt":"2020-06-15T00:00:00.000Z","startedAt":null,"state":"{\"runs\":4,\"count_total\":0,\"count_by_type\":{},\"throttle_time\":{\"min\":\"0s\",\"avg\":\"0s\",\"max\":\"0s\"},\"schedule_time\":{\"min\":\"0s\",\"avg\":\"0s\",\"max\":\"0s\"},\"connectors_per_alert\":{\"min\":0,\"avg\":0,\"max\":0},\"count_active_by_type\":{},\"count_active_total\":0,\"count_disabled_total\":0}","params":"{}","ownerId":null,"scheduledAt":"2020-06-11T21:59:07.913Z","attempts":0,"status":"idle"},"references":[],"updated_at":"2020-06-14T00:00:00.781Z","type":"task"}}
{"_index":".kibana_task_manager_1","_type":"_doc","_id":"task:Actions-actions_telemetry","_score":1,"_source":{"migrationVersion":{"task":"7.6.0"},"task":{"taskType":"actions_telemetry","retryAt":null,"runAt":"2020-06-15T00:00:00.000Z","startedAt":null,"state":"{\"runs\":4,\"count_total\":0,\"count_by_type\":{},\"count_active_total\":0}","params":"{}","ownerId":null,"scheduledAt":"2020-06-11T21:59:07.913Z","attempts":0,"status":"idle"},"references":[],"updated_at":"2020-06-14T00:00:00.776Z","type":"task"}}
{"_index":".kibana_task_manager_1","_type":"_doc","_id":"task:apm-telemetry-task","_score":1,"_source":{"migrationVersion":{"task":"7.6.0"},"task":{"schedule":{"interval":"720m"},"taskType":"apm-telemetry-task","retryAt":null,"runAt":"2020-06-15T10:07:37.474Z","scope":["apm"],"startedAt":null,"state":"{}","params":"{}","ownerId":null,"scheduledAt":"2020-06-11T21:59:07.913Z","attempts":0,"status":"idle"},"references":[],"updated_at":"2020-06-14T22:07:37.672Z","type":"task"}}
